[
  {
    "id": "24",
    "name": "89af2095c6f5ad8df11a"
  },
  {
    "id": "62",
    "name": "7f26de16b7952a568068"
  },
  {
    "id": "457",
    "name": "17a629b4578d5ac593aa"
  },
  {
    "id": "465",
    "name": "af78b2b5fe9c9b4cd113"
  },
  {
    "id": "513",
    "name": "0b4ff8846e65368e8eef"
  },
  {
    "id": "516",
    "name": "95d00f18339a395f8007"
  },
  {
    "id": "979",
    "name": "5b2d94e08eee91d70723"
  },
  {
    "id": "1025",
    "name": "b49432c82be4b615826e"
  },
  {
    "id": "1048",
    "name": "a2c25c5282d336494198"
  },
  {
    "id": "1162",
    "name": "330ba0f888e4e75a74cd"
  },
  {
    "id": "1257",
    "name": "fe5590661cfe4058ac83"
  },
  {
    "id": "1459",
    "name": "14791d7bf09bf4cf5ca5"
  },
  {
    "id": "1553",
    "name": "37adc68b8b7cfaaa2a71"
  },
  {
    "id": "1562",
    "name": "764f4bc5b7b6b60c7eae"
  },
  {
    "id": "1613",
    "name": "f8efcf3317d450a69690"
  },
  {
    "id": "1650",
    "name": "55e6348d91e0277005d2"
  },
  {
    "id": "1653",
    "name": "b58ac225ea7f4000f5da"
  },
  {
    "id": "1654",
    "name": "5f00de8180dfa9972e10"
  },
  {
    "id": "1764",
    "name": "641256dded7d2a505053"
  },
  {
    "id": "1904",
    "name": "c8046a2d37a5d5098d43"
  },
  {
    "id": "1960",
    "name": "973188969d6efe082889"
  },
  {
    "id": "2e3",
    "name": "79d1c39965f3ba793b5d"
  },
  {
    "id": "2010",
    "name": "741162383135dfbe4ba2"
  },
  {
    "id": "2139",
    "name": "1f6a14f7a4df25048b2d"
  },
  {
    "id": "2231",
    "name": "6556b618167bae5d3e97"
  },
  {
    "id": "2461",
    "name": "7607df48124c8fc93129"
  },
  {
    "id": "2573",
    "name": "cf759024171fa6f6943d"
  },
  {
    "id": "2955",
    "name": "454d77e0a113cb013385"
  },
  {
    "id": "3039",
    "name": "7a1f88e13ebd94c3eb75"
  },
  {
    "id": "3404",
    "name": "4a8eef14de939c82dbd2"
  },
  {
    "id": "3541",
    "name": "5bb5b1c873dbea3f7e56"
  },
  {
    "id": "3790",
    "name": "32ca0c7ace2d1a9c8891"
  },
  {
    "id": "3824",
    "name": "148fa62d44837be85caa"
  },
  {
    "id": "4018",
    "name": "0b7861fb0cc2a1698302"
  },
  {
    "id": "4032",
    "name": "c20ce40fd8566cee5288"
  },
  {
    "id": "4070",
    "name": "85b1567e33bc73134920"
  },
  {
    "id": "4392",
    "name": "f9e98c9d34a644dc6ce0"
  },
  {
    "id": "4423",
    "name": "c795700fe992effc8998"
  },
  {
    "id": "4483",
    "name": "bf8c654a6695dfbc2171"
  },
  {
    "id": "4593",
    "name": "5c0096ec6b2c534ecf5a"
  },
  {
    "id": "4767",
    "name": "05d3e6c75fbf61b06196"
  },
  {
    "id": "4782",
    "name": "1c0eb4ba27904051126e"
  },
  {
    "id": "4909",
    "name": "30593281d6b4cd356d01"
  },
  {
    "id": "5126",
    "name": "d98fcaa86a1394429ae3"
  },
  {
    "id": "5496",
    "name": "84339edb7aac1e5eedcc"
  },
  {
    "id": "5522",
    "name": "c68884f9aed75644daf8"
  },
  {
    "id": "5549",
    "name": "6e0ab17580a829552e8f"
  },
  {
    "id": "6331",
    "name": "27069da7f336cf71a18f"
  },
  {
    "id": "6341",
    "name": "46139690b36bcf971ee5"
  },
  {
    "id": "6543",
    "name": "5917913a573e344ea884"
  },
  {
    "id": "6565",
    "name": "279c776580057b10f8ce"
  },
  {
    "id": "6578",
    "name": "88cc9898cae7388bf642"
  },
  {
    "id": "6652",
    "name": "0d1a4fea5f5caa9aa4da"
  },
  {
    "id": "6825",
    "name": "28816b3c8b45057cc083"
  },
  {
    "id": "6834",
    "name": "b256f702c57346f266e6"
  },
  {
    "id": "6944",
    "name": "f23654f2ff038a2c336e"
  },
  {
    "id": "7088",
    "name": "880e6f5b57ff55720f00"
  },
  {
    "id": "7427",
    "name": "65ba02458abcb0acdc30"
  },
  {
    "id": "7434",
    "name": "3f02a9c638d6efdb29e4"
  },
  {
    "id": "7510",
    "name": "d1a18ce4ebfb31e7ffdd"
  },
  {
    "id": "7528",
    "name": "71e333f889f797b5e2ca"
  },
  {
    "id": "7544",
    "name": "101842e4d9683f3aa2cd"
  },
  {
    "id": "7679",
    "name": "d9fe3004586842177a7f"
  },
  {
    "id": "7727",
    "name": "2f358f0a906cb6215d80"
  },
  {
    "id": "7811",
    "name": "cf978c67867a40738166"
  },
  {
    "id": "7849",
    "name": "5f190d728fad96feb952"
  },
  {
    "id": "7939",
    "name": "ca7eb51ba1685fd8c27c"
  },
  {
    "id": "7947",
    "name": "904ac5609fa141773d9a"
  },
  {
    "id": "8056",
    "name": "c092a43062906226dd51"
  },
  {
    "id": "8197",
    "name": "47034b2a1003c397c467"
  },
  {
    "id": "8276",
    "name": "24e4571b5e65bc1b4e36"
  },
  {
    "id": "8388",
    "name": "8e1fc9a8e4da557340e5"
  },
  {
    "id": "8440",
    "name": "291e15478fe3f876bcbe"
  },
  {
    "id": "9096",
    "name": "e19d7a2f3dcb1bbcbdcf"
  },
  {
    "id": "9183",
    "name": "592cb9976c741edade88"
  },
  {
    "id": "9244",
    "name": "1a70ed7bba44e36f1bb5"
  },
  {
    "id": "9355",
    "name": "e9153eb79dbfc10ada92"
  },
  {
    "id": "9582",
    "name": "165faa0b8d2572098541"
  },
  {
    "id": "9608",
    "name": "402f6d61d0c6e70b3f74"
  },
  {
    "id": "9749",
    "name": "0fe25e8032e8372b7956"
  },
  {
    "id": "10504",
    "name": "c4b0c7cb80f0885b0642"
  },
  {
    "id": "10523",
    "name": "efc1fef22caf2c7714a1"
  },
  {
    "id": "10541",
    "name": "41392a29af8b2c6f2de2"
  },
  {
    "id": "10545",
    "name": "97ff97d664bf0f86de20"
  },
  {
    "id": "10648",
    "name": "7ed06d0c0e1d3abf8c59"
  },
  {
    "id": "10675",
    "name": "63593f6df157bae62e26"
  },
  {
    "id": "10790",
    "name": "1fac356d776cd5ff478a"
  },
  {
    "id": "10832",
    "name": "6facc2ca5bc8f59a7248"
  },
  {
    "id": "10845",
    "name": "4c7759a02b5c0690c9eb"
  },
  {
    "id": "10848",
    "name": "8765d2deea5f79d144d3"
  },
  {
    "id": "11177",
    "name": "c69d10d78d4a9baf8b06"
  },
  {
    "id": "11248",
    "name": "da2681d321543aac9b90"
  },
  {
    "id": "11261",
    "name": "45724341d4defb0a0725"
  },
  {
    "id": "11266",
    "name": "0e3229a8405006eb9da4"
  },
  {
    "id": "11569",
    "name": "71bf5c0f3b4007f1ee4a"
  },
  {
    "id": "11731",
    "name": "accfb96d59c68151b42a"
  },
  {
    "id": "11860",
    "name": "b3b3f65f3fcba29e5240"
  },
  {
    "id": "11913",
    "name": "db47cda5530b56825d6d"
  },
  {
    "id": "12141",
    "name": "6d68ef92a006a4acbc1d"
  },
  {
    "id": "12295",
    "name": "9cdf03b94269d21d7c66"
  },
  {
    "id": "12586",
    "name": "d8fb55891fa49b92e115"
  },
  {
    "id": "12671",
    "name": "74d0ea63ab37d3118fc0"
  },
  {
    "id": "12702",
    "name": "14d663a99f1a6ca36572"
  },
  {
    "id": "12777",
    "name": "d8e1b098460e2e3b8487"
  },
  {
    "id": "13035",
    "name": "876c85ecf9bf42289656"
  },
  {
    "id": "13185",
    "name": "23d149390afebce807bf"
  },
  {
    "id": "13255",
    "name": "122f1a318bc848b44caa"
  },
  {
    "id": "13621",
    "name": "70662063495ffbf27700"
  },
  {
    "id": "13777",
    "name": "4f9c508a86ce9c971d96"
  },
  {
    "id": "14136",
    "name": "d73298bbd0d469ab6cc3"
  },
  {
    "id": "14203",
    "name": "6ba6b4ce0f0018fb3e8e"
  },
  {
    "id": "14284",
    "name": "7c0c5c57673ae8c1a7f5"
  },
  {
    "id": "14288",
    "name": "16f338232a61739233ec"
  },
  {
    "id": "14372",
    "name": "78d73ea1462ad402856c"
  },
  {
    "id": "14449",
    "name": "f90b3148c47b0917ee33"
  },
  {
    "id": "14594",
    "name": "b3c311aa611a5ca3a353"
  },
  {
    "id": "14844",
    "name": "d34af00796221e233f6b"
  },
  {
    "id": "14891",
    "name": "6c5bfb53870a5e602826"
  },
  {
    "id": "15339",
    "name": "98fd5abe83ce8925c71e"
  },
  {
    "id": "15434",
    "name": "53c9996b7b35e024a2af"
  },
  {
    "id": "15550",
    "name": "d2e2e3e17f2271fe8055"
  },
  {
    "id": "15725",
    "name": "c28a45157217f0c06c69"
  },
  {
    "id": "15760",
    "name": "592ed3f1d07f766af112"
  },
  {
    "id": "15985",
    "name": "9b4c41d52885c955928a"
  },
  {
    "id": "16139",
    "name": "1fb5745f7e387b77886b"
  },
  {
    "id": "16248",
    "name": "459910aa9945ad1be959"
  },
  {
    "id": "16561",
    "name": "400673741c492ec43de5"
  },
  {
    "id": "16673",
    "name": "3ad1e1b2d4e66e669ff3"
  },
  {
    "id": "16779",
    "name": "395088ae7f3b476ee1fb"
  },
  {
    "id": "16841",
    "name": "a8dbe7d851ef8209e8a9"
  },
  {
    "id": "17081",
    "name": "af899fcf49931d220420"
  },
  {
    "id": "17251",
    "name": "3447fd97904d93700ae9"
  },
  {
    "id": "17363",
    "name": "95241bcacfe8576190eb"
  },
  {
    "id": "17410",
    "name": "5534d336285e5251c179"
  },
  {
    "id": "17469",
    "name": "5c52f49b2109e299540e"
  },
  {
    "id": "17517",
    "name": "fa920cc99e103c9f44a8"
  },
  {
    "id": "17586",
    "name": "80ecc1bb4921e3e5ce0c"
  },
  {
    "id": "17592",
    "name": "296a7205e1041713f0d7"
  },
  {
    "id": "17667",
    "name": "ebb65abadeccfe52b132"
  },
  {
    "id": "17854",
    "name": "797fc49674f5a25cc14e"
  },
  {
    "id": "17864",
    "name": "53dbc94daa382d8de01d"
  },
  {
    "id": "18079",
    "name": "ec1101cbf9742c7dfcd0"
  },
  {
    "id": "18354",
    "name": "3f1fd0bbe38cc8d63ebb"
  },
  {
    "id": "18359",
    "name": "a01d847f377a83c6c4fc"
  },
  {
    "id": "18361",
    "name": "e8440d7f6bb92b0fb85b"
  },
  {
    "id": "18407",
    "name": "6d4d3bb075170298f3a0"
  },
  {
    "id": "18442",
    "name": "b1785d10e5f15c5c6d3d"
  },
  {
    "id": "18470",
    "name": "cadcdd0fa5efdae75b2b"
  },
  {
    "id": "18554",
    "name": "754a77807edb595365b9"
  },
  {
    "id": "18625",
    "name": "d22cbf7c26df79eb5937"
  },
  {
    "id": "18682",
    "name": "bdb8192678e2ff7d486b"
  },
  {
    "id": "18797",
    "name": "a7499ed8e4378ead2942"
  },
  {
    "id": "19431",
    "name": "6562407fa190de02e759"
  },
  {
    "id": "19493",
    "name": "ac4e2d3f842792785672"
  },
  {
    "id": "19507",
    "name": "1e2524541367366a89e8"
  },
  {
    "id": "19595",
    "name": "5332f13d7ed324a32ec9"
  },
  {
    "id": "19763",
    "name": "2f243384766a0417e24b"
  },
  {
    "id": "19887",
    "name": "71481fed526301cf88ff"
  },
  {
    "id": "20188",
    "name": "b07ded5b43c70508ced6"
  },
  {
    "id": "20419",
    "name": "2c77afae0022450611ce"
  },
  {
    "id": "20486",
    "name": "df348e0efcd60c9d034c"
  },
  {
    "id": "20554",
    "name": "fab5d2fbd342eda644f9"
  },
  {
    "id": "20637",
    "name": "c84a2f4d52dd27b3b1f4"
  },
  {
    "id": "20737",
    "name": "ca9bda94445e70192c2d"
  },
  {
    "id": "20907",
    "name": "626ac7c5af5525f1ff89"
  },
  {
    "id": "20995",
    "name": "559de58337054aefdcd2"
  },
  {
    "id": "21145",
    "name": "b7d3afb62b5b8e75124f"
  },
  {
    "id": "21171",
    "name": "3366a46bca8be4bfe01f"
  },
  {
    "id": "21215",
    "name": "5330757f027869b2875c"
  },
  {
    "id": "21297",
    "name": "cce2142adc6c39583ef2"
  },
  {
    "id": "21373",
    "name": "bc9f9480a3bbf2498fc3"
  },
  {
    "id": "21375",
    "name": "133e96d609828ba772f2"
  },
  {
    "id": "21391",
    "name": "57c98f688a726318a517"
  },
  {
    "id": "21504",
    "name": "d2a03de24e2653379427"
  },
  {
    "id": "21588",
    "name": "1719179d7719a813a293"
  },
  {
    "id": "21633",
    "name": "ccf24aa93257cc27bacd"
  },
  {
    "id": "21644",
    "name": "e2d0e2e4eab929c3b0bb"
  },
  {
    "id": "21723",
    "name": "8f04b9f068d07860b8ca"
  },
  {
    "id": "21786",
    "name": "8c4d61755d471aaa1f69"
  },
  {
    "id": "21819",
    "name": "4dd3010dd911c6fd05d8"
  },
  {
    "id": "21859",
    "name": "726addd980847e7482fb"
  },
  {
    "id": "22010",
    "name": "d09b8bdbdffc7f53722f"
  },
  {
    "id": "22170",
    "name": "5fb0fd31c4166300fb33"
  },
  {
    "id": "22251",
    "name": "7f27631d6bb7c796b139"
  },
  {
    "id": "22325",
    "name": "a7835c6d6596facf8a91"
  },
  {
    "id": "22513",
    "name": "0a036178bc42a4f848ce"
  },
  {
    "id": "22587",
    "name": "29867527ee42ee2c0aeb"
  },
  {
    "id": "23286",
    "name": "3956b7975a2ca2581ccc"
  },
  {
    "id": "23527",
    "name": "8f62cf93f186ce78b0e4"
  },
  {
    "id": "23725",
    "name": "bf634642629cfc671c09"
  },
  {
    "id": "23783",
    "name": "c29380531fd319407a3d"
  },
  {
    "id": "23850",
    "name": "71c31e381a7d288a474c"
  },
  {
    "id": "24209",
    "name": "b13172cb22d68744a3e9"
  },
  {
    "id": "24251",
    "name": "cb07aa052e667dbc18a7"
  },
  {
    "id": "24278",
    "name": "0d4c7e28ab602fa176bc"
  },
  {
    "id": "24285",
    "name": "d94eb96d4d2752daded1"
  },
  {
    "id": "24333",
    "name": "910d21f281ef726de743"
  },
  {
    "id": "24417",
    "name": "6efddfafadf8ec2e8584"
  },
  {
    "id": "24501",
    "name": "d22e17beb967705a183a"
  },
  {
    "id": "24561",
    "name": "45e98a7874ebfe04a688"
  },
  {
    "id": "24567",
    "name": "3d9917d7dececbb9ee4e"
  },
  {
    "id": "24570",
    "name": "70b651a53b3b7126fe69"
  },
  {
    "id": "24971",
    "name": "74fd042ce9911b251976"
  },
  {
    "id": "25033",
    "name": "e2c924a137694b3adfcd"
  },
  {
    "id": "25051",
    "name": "35f62d05526d1e435cbe"
  },
  {
    "id": "25289",
    "name": "bebdd11bd0d20f74db76"
  },
  {
    "id": "25312",
    "name": "f97202031ca8338a658b"
  },
  {
    "id": "25395",
    "name": "f36d4bc0fb3eaddbb65b"
  },
  {
    "id": "25513",
    "name": "ce02b2bdc73a963ad9a2"
  },
  {
    "id": "25978",
    "name": "f28a8bf803193d23f7c8"
  },
  {
    "id": "26136",
    "name": "ab2065b9f8694d601460"
  },
  {
    "id": "26298",
    "name": "2dfd6e7f305854b3b229"
  },
  {
    "id": "26473",
    "name": "9bf95fd9c5bdac74496d"
  },
  {
    "id": "26546",
    "name": "97e569d6ab43889374c0"
  },
  {
    "id": "26719",
    "name": "44c65444cbd944d62ecc"
  },
  {
    "id": "26945",
    "name": "5c83c8e702683d7845bd"
  },
  {
    "id": "27051",
    "name": "fa6487b4603cbfe7b088"
  },
  {
    "id": "27059",
    "name": "03e3c86fd547b8978d01"
  },
  {
    "id": "27077",
    "name": "24c6642a896046b9ccba"
  },
  {
    "id": "27096",
    "name": "eb60c76df73f61a8c247"
  },
  {
    "id": "27134",
    "name": "b83099855de3d917bfee"
  },
  {
    "id": "27314",
    "name": "9f5eb83c6e1300994762"
  },
  {
    "id": "27373",
    "name": "0960a1fc96b4efd60bc1"
  },
  {
    "id": "27392",
    "name": "58b0d0d4973767c487ab"
  },
  {
    "id": "27477",
    "name": "359ac181bd13243fa77b"
  },
  {
    "id": "27499",
    "name": "aacfdd7567bc83d8a298"
  },
  {
    "id": "27608",
    "name": "90c6685a780062f1ee2e"
  },
  {
    "id": "27684",
    "name": "19b552c09e0ff6354f90"
  },
  {
    "id": "27713",
    "name": "efd0d88770721adeabd0"
  },
  {
    "id": "27979",
    "name": "fbdce0f2fdb1679b81bb"
  },
  {
    "id": "28e3",
    "name": "a1475f78895a13c75c69"
  },
  {
    "id": "28008",
    "name": "dcd935180bfde25409ed"
  },
  {
    "id": "28081",
    "name": "247d0ee3f967e13d9217"
  },
  {
    "id": "28478",
    "name": "7b334c8311cf71213e9a"
  },
  {
    "id": "28562",
    "name": "7f166af13589ff5ae649"
  },
  {
    "id": "28629",
    "name": "4fc63329a84c9c726a09"
  },
  {
    "id": "28746",
    "name": "9dba21f615671ea2adb0"
  },
  {
    "id": "29021",
    "name": "9e2251e6186b7f520307"
  },
  {
    "id": "29197",
    "name": "577b5bf6696b465bcc40"
  },
  {
    "id": "29202",
    "name": "3ece3058927aada199e1"
  },
  {
    "id": "29253",
    "name": "7a252a52b3dd7fe835f1"
  },
  {
    "id": "29342",
    "name": "776e14f7bb516bb459b1"
  },
  {
    "id": "29375",
    "name": "90fa7f049878dde5a4de"
  },
  {
    "id": "29392",
    "name": "4a990ee395eff025febb"
  },
  {
    "id": "29581",
    "name": "9be231e49de3f1edc6d6"
  },
  {
    "id": "29615",
    "name": "b4319d9cd45fbca62977"
  },
  {
    "id": "29856",
    "name": "ee541bf40e45671f1997"
  },
  {
    "id": "30027",
    "name": "7215fa4df7bcda4dba83"
  },
  {
    "id": "30144",
    "name": "402c88a57e6c361e3b18"
  },
  {
    "id": "30269",
    "name": "c728e0dd2698bc56d0ba"
  },
  {
    "id": "30402",
    "name": "70ac64f42c9ddc371168"
  },
  {
    "id": "30452",
    "name": "2bf40061a379d2aa747d"
  },
  {
    "id": "30685",
    "name": "d42fe1fc20773eb71ac2"
  },
  {
    "id": "30695",
    "name": "c21b9e5ed80ff5a6479d"
  },
  {
    "id": "30731",
    "name": "1993df945448f3a06f5a"
  },
  {
    "id": "30766",
    "name": "106712afc3ec5adad1b5"
  },
  {
    "id": "31186",
    "name": "f63157250bdaf87e321f"
  },
  {
    "id": "31198",
    "name": "f2c1e08950df3b2f63bb"
  },
  {
    "id": "31203",
    "name": "3db734444e8ac2264747"
  },
  {
    "id": "31480",
    "name": "b10e38a43a39d2bbb478"
  },
  {
    "id": "31488",
    "name": "2d1eae0a60b542e85b77"
  },
  {
    "id": "31499",
    "name": "8f8521df55f92c4b2fc8"
  },
  {
    "id": "31500",
    "name": "726279ee710c1c185638"
  },
  {
    "id": "31520",
    "name": "273e427fdb1b42998ab4"
  },
  {
    "id": "31649",
    "name": "515261b67947c9b53ddc"
  },
  {
    "id": "31667",
    "name": "dff3f6e595616ddf1406"
  },
  {
    "id": "32013",
    "name": "d7f6f82132362664f6b2"
  },
  {
    "id": "32014",
    "name": "fae16945fe99dda52b5d"
  },
  {
    "id": "32027",
    "name": "b459473956e4b4b76f41"
  },
  {
    "id": "32041",
    "name": "a87d63aaffd7fcd55a9c"
  },
  {
    "id": "32162",
    "name": "4e03d696069df5a1f565"
  },
  {
    "id": "32282",
    "name": "473d27d337f9c268614c"
  },
  {
    "id": "32632",
    "name": "e0c95195ec6552923007"
  },
  {
    "id": "32859",
    "name": "d63782bc7fa90bd62c37"
  },
  {
    "id": "32978",
    "name": "5507cbcbd857d5302d57"
  },
  {
    "id": "33086",
    "name": "57e04c5109bdedf5603c"
  },
  {
    "id": "33166",
    "name": "2c4f36bf0f4bca5d2402"
  },
  {
    "id": "33227",
    "name": "970e8e4b0740d65185f3"
  },
  {
    "id": "33600",
    "name": "a2d6597d23e556ac04de"
  },
  {
    "id": "33735",
    "name": "35bc5743e023a86f21d5"
  },
  {
    "id": "33970",
    "name": "fd69216b987718bdec8e"
  },
  {
    "id": "34165",
    "name": "1bb2378746fb3f8d0eef"
  },
  {
    "id": "34495",
    "name": "0cca5b9daf02ca975f0f"
  },
  {
    "id": "34661",
    "name": "e20edebfb472dca5bf1b"
  },
  {
    "id": "34757",
    "name": "50528c2775567bf5b50f"
  },
  {
    "id": "34840",
    "name": "c03dcb34201d3e70188e"
  },
  {
    "id": "35521",
    "name": "e4a8b2330813c65d7cf3"
  },
  {
    "id": "35579",
    "name": "0744fef111c6df94dfe6"
  },
  {
    "id": "35612",
    "name": "5f8ffc3d5cf5be1324b2"
  },
  {
    "id": "35650",
    "name": "215285bb41602c007ca7"
  },
  {
    "id": "35657",
    "name": "d20fb42af08e70001d7a"
  },
  {
    "id": "35743",
    "name": "ee1788e30ffe28c4b591"
  },
  {
    "id": "35751",
    "name": "eab04cc80db122c3f909"
  },
  {
    "id": "35780",
    "name": "bc3ee887015d620cbd8f"
  },
  {
    "id": "35796",
    "name": "14da53227c6e25fca780"
  },
  {
    "id": "35804",
    "name": "35876455f3e94ee389f5"
  },
  {
    "id": "35923",
    "name": "a8bc2ad3a24c2f267bed"
  },
  {
    "id": "36164",
    "name": "1ab309862938d3cc0187"
  },
  {
    "id": "36181",
    "name": "37de95f4a90aa844056b"
  },
  {
    "id": "36623",
    "name": "2995cfe3cb74e04a5cd2"
  },
  {
    "id": "36759",
    "name": "98b7502210a514526927"
  },
  {
    "id": "36817",
    "name": "e6f15a5a24ec5070403b"
  },
  {
    "id": "36829",
    "name": "d6539fa310c738db9cf0"
  },
  {
    "id": "37246",
    "name": "b9da462afd23e6977a10"
  },
  {
    "id": "37311",
    "name": "59961eab8bd072f2c7d5"
  },
  {
    "id": "37375",
    "name": "8b8599a660497afff7b2"
  },
  {
    "id": "37452",
    "name": "742a8e5271c5353fb115"
  },
  {
    "id": "37464",
    "name": "903670d265869e4ff239"
  },
  {
    "id": "37761",
    "name": "ed01ec7d4ec17d539063"
  },
  {
    "id": "37897",
    "name": "5f3d2261bffdd446d472"
  },
  {
    "id": "37948",
    "name": "4d3282d95a41eb1dee46"
  },
  {
    "id": "38039",
    "name": "fc98cd1b3036d5ce8393"
  },
  {
    "id": "38092",
    "name": "e5de7025a38ba8a0e915"
  },
  {
    "id": "38104",
    "name": "e281ddfe4a3ada52fc9e"
  },
  {
    "id": "38153",
    "name": "7404884d684f91321e1c"
  },
  {
    "id": "38175",
    "name": "d3a3288e07425f0b957f"
  },
  {
    "id": "38212",
    "name": "c6769c7b8405f1caac90"
  },
  {
    "id": "38379",
    "name": "f44f9cfb51e9a1eb1b6e"
  },
  {
    "id": "38479",
    "name": "59b5db775a3ef1fd0141"
  },
  {
    "id": "38501",
    "name": "ae06e332f26f9e3b8a4d"
  },
  {
    "id": "38525",
    "name": "8543fe7c3b2c44340b11"
  },
  {
    "id": "38599",
    "name": "37a141b3b96ad90960f1"
  },
  {
    "id": "38634",
    "name": "8f6accf348222a5da83d"
  },
  {
    "id": "38657",
    "name": "129131f204f148bff223"
  },
  {
    "id": "38813",
    "name": "a5a368d6abfd757ed18d"
  },
  {
    "id": "38826",
    "name": "45cb7b5ce211a015e871"
  },
  {
    "id": "38845",
    "name": "f86eebbb844fe10f8e44"
  },
  {
    "id": "39023",
    "name": "d58a1c8fa59f68b6d4a3"
  },
  {
    "id": "39101",
    "name": "8c0e27211b9b12633515"
  },
  {
    "id": "39354",
    "name": "1846adb1aedfd4671241"
  },
  {
    "id": "39685",
    "name": "af67a9b0873abdcd5bd0"
  },
  {
    "id": "39750",
    "name": "1cb5cdbf8e95494b1306"
  },
  {
    "id": "39810",
    "name": "e2b6dc181a060cdc5fb2"
  },
  {
    "id": "39814",
    "name": "bcb96db4f97970211ba4"
  },
  {
    "id": "39874",
    "name": "77cfc7ba8984024b3d2c"
  },
  {
    "id": "39876",
    "name": "99df7d80ab47f04c6239"
  },
  {
    "id": "39915",
    "name": "b232aa83ea5fa3ff7761"
  },
  {
    "id": "40056",
    "name": "d12a6ff98edc761afcfb"
  },
  {
    "id": "40532",
    "name": "96c2a21127cb43c94d21"
  },
  {
    "id": "40706",
    "name": "641170a62b5c4fa57653"
  },
  {
    "id": "41098",
    "name": "77f7d0cfc37ef88cdbdb"
  },
  {
    "id": "41394",
    "name": "2a6446deabdc810b17d3"
  },
  {
    "id": "41446",
    "name": "7293692d274b6c018269"
  },
  {
    "id": "41484",
    "name": "8a1e4a0c774be2821773"
  },
  {
    "id": "41491",
    "name": "fa379c2b7989c550e112"
  },
  {
    "id": "41666",
    "name": "e8dcb57af1cbedfc13d5"
  },
  {
    "id": "41818",
    "name": "02fe8409b9610281731b"
  },
  {
    "id": "42193",
    "name": "4caee51234bc1c45ed42"
  },
  {
    "id": "42310",
    "name": "2d9970c074d2d9801aaf"
  },
  {
    "id": "42341",
    "name": "1f46d1abf1de14c7b0b3"
  },
  {
    "id": "42426",
    "name": "7f47cd1709d33a490c2a"
  },
  {
    "id": "42660",
    "name": "762477b2266c792eab04"
  },
  {
    "id": "42762",
    "name": "a0472c6c62cd838069d1"
  },
  {
    "id": "42867",
    "name": "66beec07e32f647f1f2c"
  },
  {
    "id": "43043",
    "name": "a23c8ca5dbdd95e7ba7b"
  },
  {
    "id": "43244",
    "name": "e838bd453827ee8fe1c2"
  },
  {
    "id": "43315",
    "name": "087d9d91a5e21d897641"
  },
  {
    "id": "43372",
    "name": "9a1e580d3f4832e68098"
  },
  {
    "id": "43402",
    "name": "8255552a645d6706b2e6"
  },
  {
    "id": "43411",
    "name": "87c5fac268ec747f6802"
  },
  {
    "id": "43470",
    "name": "20e05570e743227c38cc"
  },
  {
    "id": "43569",
    "name": "e2beac4fcee8807ac8a2"
  },
  {
    "id": "43754",
    "name": "28684a67eaa3706d86e6"
  },
  {
    "id": "43814",
    "name": "f1673e97182d27b9bd39"
  },
  {
    "id": "43929",
    "name": "8022f7b48c5dcddfa3cd"
  },
  {
    "id": "43942",
    "name": "75ec547d89fb375c4e35"
  },
  {
    "id": "44018",
    "name": "5b8c5f461ac9ee42d752"
  },
  {
    "id": "44230",
    "name": "021d6b5a4a65caf61b5f"
  },
  {
    "id": "44235",
    "name": "74dbd4df4de3f23ac298"
  },
  {
    "id": "44338",
    "name": "53a3f422098b74a3cdff"
  },
  {
    "id": "44339",
    "name": "a3269187051b88aa8a97"
  },
  {
    "id": "44522",
    "name": "0480e72faa36862a29fe"
  },
  {
    "id": "44696",
    "name": "d0b323fcd5decb6f1d3a"
  },
  {
    "id": "44829",
    "name": "b3c1e48fad1ad9b9e50c"
  },
  {
    "id": "44832",
    "name": "06a75f9a55bf8a9a8cdc"
  },
  {
    "id": "44951",
    "name": "e0aadcf81c2f6874a9e2"
  },
  {
    "id": "44953",
    "name": "0668318bd5b06285948b"
  },
  {
    "id": "45313",
    "name": "72790db4ecd100eeac9d"
  },
  {
    "id": "45353",
    "name": "697433ff0a00375283bd"
  },
  {
    "id": "45482",
    "name": "14c743b30619f2de8bd7"
  },
  {
    "id": "45660",
    "name": "a10b8eb99c97b00b3542"
  },
  {
    "id": "45716",
    "name": "83808bdcdaa97b15cc71"
  },
  {
    "id": "46007",
    "name": "348f50513383c15e7824"
  },
  {
    "id": "46070",
    "name": "535c5f761f69f4c73515"
  },
  {
    "id": "46194",
    "name": "1074f0a559030189a9c0"
  },
  {
    "id": "46197",
    "name": "695b2dc937bfb5abd59e"
  },
  {
    "id": "46208",
    "name": "7c1c8dcd0ab3265f9b82"
  },
  {
    "id": "46285",
    "name": "8ac1278fab9ad8bfe024"
  },
  {
    "id": "46559",
    "name": "20bedd23618d54b4a733"
  },
  {
    "id": "46738",
    "name": "57b0af1acd77b525797b"
  },
  {
    "id": "46903",
    "name": "ed18482041c39299c122"
  },
  {
    "id": "46962",
    "name": "f9e68b3577c2c846841c"
  },
  {
    "id": "47007",
    "name": "5542fefd7b125f21c5d0"
  },
  {
    "id": "47035",
    "name": "6ff9987db728a85c7b3c"
  },
  {
    "id": "47057",
    "name": "94965e6eb275bc4486ae"
  },
  {
    "id": "47114",
    "name": "02ef577e32b18f14c1b7"
  },
  {
    "id": "47311",
    "name": "bde913a358524a8ab7bb"
  },
  {
    "id": "47405",
    "name": "5c55ae37cc0ff6e544b4"
  },
  {
    "id": "47428",
    "name": "b2ad37e4d3993a034e1a"
  },
  {
    "id": "47701",
    "name": "d5f6522db26f5dbc275a"
  },
  {
    "id": "47722",
    "name": "c8940e41bd35219159f5"
  },
  {
    "id": "47749",
    "name": "406b967c2b0159a552b5"
  },
  {
    "id": "47797",
    "name": "3ce7eb4b5c2d9dba3cde"
  },
  {
    "id": "47935",
    "name": "7c51aff164bcd7419633"
  },
  {
    "id": "48137",
    "name": "3e66a418e9455cd4da36"
  },
  {
    "id": "48152",
    "name": "9cafb227c9c9a8bad745"
  },
  {
    "id": "48372",
    "name": "e2ef33f1a26478f3bdef"
  },
  {
    "id": "48448",
    "name": "3b7f02f9ab3cac11fc1c"
  },
  {
    "id": "48544",
    "name": "f89281a35f84a730b9e7"
  },
  {
    "id": "49151",
    "name": "0deff400423c65feef26"
  },
  {
    "id": "49244",
    "name": "1e98c684992a8a56966b"
  },
  {
    "id": "49393",
    "name": "c7bd4c576b7641169369"
  },
  {
    "id": "49607",
    "name": "5893063cf9b8e9fe60ca"
  },
  {
    "id": "49667",
    "name": "22e973215089478b781b"
  },
  {
    "id": "49719",
    "name": "b0a935e0d912e166d016"
  },
  {
    "id": "49770",
    "name": "bb1df27a266b1806fbad"
  },
  {
    "id": "49799",
    "name": "b187540bd5eab0ebf7eb"
  },
  {
    "id": "50526",
    "name": "30484814b2eca79795dc"
  },
  {
    "id": "50562",
    "name": "7d933e14c762b18ec749"
  },
  {
    "id": "50603",
    "name": "a239f7b3ec5b2ee86c12"
  },
  {
    "id": "50648",
    "name": "baa1039fe6d1a4bde0ad"
  },
  {
    "id": "50865",
    "name": "ab6a1e86ec106c8e8c7b"
  },
  {
    "id": "51388",
    "name": "5b9daa53e8f35b0bd3ca"
  },
  {
    "id": "51395",
    "name": "01101536a3a7921bae18"
  },
  {
    "id": "51459",
    "name": "72ae77649b998501ab57"
  },
  {
    "id": "51463",
    "name": "0aea06e07109fadb8662"
  },
  {
    "id": "51562",
    "name": "0789bfe87ff168b6211a"
  },
  {
    "id": "51691",
    "name": "58a64f5d886d98af8694"
  },
  {
    "id": "51719",
    "name": "eb71603909363255ca7a"
  },
  {
    "id": "51775",
    "name": "cf16ea5f23a6955f72e7"
  },
  {
    "id": "51889",
    "name": "6c4fca25b4186551b5bd"
  },
  {
    "id": "51954",
    "name": "407ce988c2909cd97c21"
  },
  {
    "id": "52050",
    "name": "cda6bef9196d1e9242cf"
  },
  {
    "id": "52171",
    "name": "0b7a031b42e0aad3fb05"
  },
  {
    "id": "52202",
    "name": "c7dc37c4376c12db5924"
  },
  {
    "id": "52216",
    "name": "053dc4e27270aab84977"
  },
  {
    "id": "52337",
    "name": "c1459fc1dfe43a7fdc10"
  },
  {
    "id": "52386",
    "name": "66c11351da93603d4d14"
  },
  {
    "id": "52555",
    "name": "d3c8dace8d9a8c40f6fb"
  },
  {
    "id": "53172",
    "name": "297f81b7283872feb92b"
  },
  {
    "id": "53572",
    "name": "cf29d1236421ca2cde48"
  },
  {
    "id": "53685",
    "name": "ffbb41e8e447179dd76f"
  },
  {
    "id": "53686",
    "name": "06c5cebcded97892b449"
  },
  {
    "id": "54048",
    "name": "32eae4d2139f9a81b551"
  },
  {
    "id": "54104",
    "name": "108de49ef7778349029a"
  },
  {
    "id": "54123",
    "name": "43b2e3a18dadafb03fa2"
  },
  {
    "id": "54143",
    "name": "591f9d4d6766d47782ff"
  },
  {
    "id": "54184",
    "name": "67dd7709246afe1e473b"
  },
  {
    "id": "54313",
    "name": "07409ed905924eeabdd0"
  },
  {
    "id": "54368",
    "name": "acb7589f0f2cd10c0562"
  },
  {
    "id": "54533",
    "name": "14a83e0bc1147916be0f"
  },
  {
    "id": "54602",
    "name": "b98bdaa0c935c6c0c166"
  },
  {
    "id": "54690",
    "name": "27aa69bd2175f44fb821"
  },
  {
    "id": "54732",
    "name": "855261de2b69a8b61db0"
  },
  {
    "id": "54776",
    "name": "60272411587d31ae791a"
  },
  {
    "id": "54886",
    "name": "7c07b1b2ba83b0897d47"
  },
  {
    "id": "55052",
    "name": "5aa46c32e62185536ac6"
  },
  {
    "id": "55201",
    "name": "c2af21e9164c49d27fee"
  },
  {
    "id": "55363",
    "name": "3a6c4376d4005371fe1a"
  },
  {
    "id": "55571",
    "name": "e65208f27a9f7458a3de"
  },
  {
    "id": "55581",
    "name": "8753ddb96144b4b9ed9b"
  },
  {
    "id": "55887",
    "name": "af42ec69d4677097e7fc"
  },
  {
    "id": "55913",
    "name": "d66c202f7409d2b3f7a1"
  },
  {
    "id": "56054",
    "name": "1cc56010c6e098c78c76"
  },
  {
    "id": "56167",
    "name": "7edcf8bae8c64707c98b"
  },
  {
    "id": "56248",
    "name": "0dfc28365dd73fb463a6"
  },
  {
    "id": "56269",
    "name": "ea5f56ceabfb2dcac6cd"
  },
  {
    "id": "56450",
    "name": "068464085f8d5972beba"
  },
  {
    "id": "56492",
    "name": "d0d3f42baed677512736"
  },
  {
    "id": "56576",
    "name": "fe7a36a23b155a589300"
  },
  {
    "id": "56591",
    "name": "8002ed73e922e4141ffe"
  },
  {
    "id": "56620",
    "name": "567a6c182f3e2988196c"
  },
  {
    "id": "56645",
    "name": "88e74a4eee2f36fda436"
  },
  {
    "id": "56674",
    "name": "b47f0a9e44004387ed72"
  },
  {
    "id": "56715",
    "name": "143c5ea7e3beeb10e292"
  },
  {
    "id": "56729",
    "name": "9691c82b357e1a8c2674"
  },
  {
    "id": "56890",
    "name": "04533f9787240e0500ea"
  },
  {
    "id": "56964",
    "name": "e661c2468b03f5ed4ad8"
  },
  {
    "id": "56992",
    "name": "dd899c1b39f1f8858bae"
  },
  {
    "id": "57092",
    "name": "71e2afd41143f007ddaf"
  },
  {
    "id": "57435",
    "name": "47f68ba30a205c53916e"
  },
  {
    "id": "57495",
    "name": "831a32a71b4ed07f64a6"
  },
  {
    "id": "57641",
    "name": "955e763f927694534c0b"
  },
  {
    "id": "57645",
    "name": "7b289b4b41c93faf36e6"
  },
  {
    "id": "58083",
    "name": "9009cb8a33e8012d4c1f"
  },
  {
    "id": "58093",
    "name": "c14f989aee53e343d423"
  },
  {
    "id": "58525",
    "name": "3fee90950ae5035514cb"
  },
  {
    "id": "58635",
    "name": "93c4325d190a169cd93b"
  },
  {
    "id": "58905",
    "name": "7d8f6f00165ebadc95d3"
  },
  {
    "id": "58969",
    "name": "52cb99f25620c7704cfd"
  },
  {
    "id": "59218",
    "name": "ae5ab4ff6c0b801585d6"
  },
  {
    "id": "59278",
    "name": "207ea30b4d339f4149e6"
  },
  {
    "id": "59295",
    "name": "bcf29e34f0823f739613"
  },
  {
    "id": "59725",
    "name": "d6dfc691840a7096a989"
  },
  {
    "id": "59818",
    "name": "4d468cc9f00e1d3f3927"
  },
  {
    "id": "59847",
    "name": "621a2a1795df021c14ff"
  },
  {
    "id": "59859",
    "name": "acf54be9e86d545dac09"
  },
  {
    "id": "59876",
    "name": "175f96245075e52e8703"
  },
  {
    "id": "60122",
    "name": "69ce19858563fba90bfe"
  },
  {
    "id": "60240",
    "name": "c6e7fefa9782c01731ba"
  },
  {
    "id": "60529",
    "name": "e99399f6fb1b65ea2f81"
  },
  {
    "id": "60575",
    "name": "1f2eae32639b75c9ca6f"
  },
  {
    "id": "60625",
    "name": "73f5cc01b07d5445478e"
  },
  {
    "id": "60652",
    "name": "2e9e081ea74597f058cd"
  },
  {
    "id": "60942",
    "name": "f324bdf45b9c461688f7"
  },
  {
    "id": "61029",
    "name": "d25ddf3ab82f901c8d3a"
  },
  {
    "id": "61304",
    "name": "03a9353ef92a1f6fb520"
  },
  {
    "id": "61645",
    "name": "06318f019f15f5e9fab9"
  },
  {
    "id": "61953",
    "name": "2e86112c0481807f883f"
  },
  {
    "id": "62389",
    "name": "1ebbdfd009b8a78c8920"
  },
  {
    "id": "62439",
    "name": "bf657af5dfec9393056a"
  },
  {
    "id": "62444",
    "name": "49b814672cbe65fdd8c9"
  },
  {
    "id": "62476",
    "name": "a58e89b3f6abe3885013"
  },
  {
    "id": "62593",
    "name": "45c1e0cfb6efc07d703d"
  },
  {
    "id": "62638",
    "name": "b945befefbe3fec4523f"
  },
  {
    "id": "62750",
    "name": "f50635f242b7f1b4c0c4"
  },
  {
    "id": "62800",
    "name": "1a30c9d9f91a101e7b08"
  },
  {
    "id": "63002",
    "name": "e604b214db3f486f32fb"
  },
  {
    "id": "63128",
    "name": "d0a43543baeef197db6d"
  },
  {
    "id": "63266",
    "name": "404f0d7578acaaafa5f0"
  },
  {
    "id": "63408",
    "name": "7c18ee12a00441c36fe7"
  },
  {
    "id": "63411",
    "name": "8e2d65bb305549348e81"
  },
  {
    "id": "63634",
    "name": "704dd0047b4acc283df3"
  },
  {
    "id": "63727",
    "name": "07a3d5042754f041d8b6"
  },
  {
    "id": "63886",
    "name": "aa8454e0efd3e8e879c3"
  },
  {
    "id": "64045",
    "name": "6c824fb0e1a3d1945a2d"
  },
  {
    "id": "64396",
    "name": "a81b56759e6f5941d7e1"
  },
  {
    "id": "64427",
    "name": "bfb455f6cadfaffa4717"
  },
  {
    "id": "64466",
    "name": "fe6cad0ad8c2205a2954"
  },
  {
    "id": "64502",
    "name": "c5c2dc4d6bad405147c4"
  },
  {
    "id": "64849",
    "name": "bb091507d0e42b8165ff"
  },
  {
    "id": "64991",
    "name": "e3ccb973b0408c592f51"
  },
  {
    "id": "65057",
    "name": "9cf4e8415b1f3da098e8"
  },
  {
    "id": "65076",
    "name": "a9e57784199d09828374"
  },
  {
    "id": "65087",
    "name": "06757588f99abff6156a"
  },
  {
    "id": "65094",
    "name": "d95ddc505edbb98cfda4"
  },
  {
    "id": "65278",
    "name": "86e0e645350461d22fcf"
  },
  {
    "id": "65650",
    "name": "43d16c59818ed17fe504"
  },
  {
    "id": "65704",
    "name": "aa53afb3c4a3a5fe05db"
  },
  {
    "id": "66058",
    "name": "ab8e37e50c79e204f20f"
  },
  {
    "id": "66334",
    "name": "b1b2742e8b19f57c5bbe"
  },
  {
    "id": "66551",
    "name": "8ccf7797a384fd013507"
  },
  {
    "id": "66658",
    "name": "7452aaf61f7d1dd80f56"
  },
  {
    "id": "66671",
    "name": "d703f1fd305890a10ea7"
  },
  {
    "id": "66683",
    "name": "282bec7a3a0e60bc1e77"
  },
  {
    "id": "66831",
    "name": "047c191ef5e0bb865ff2"
  },
  {
    "id": "66885",
    "name": "a3288060566befd31e42"
  },
  {
    "id": "67068",
    "name": "1ef247d64065aa21dacc"
  },
  {
    "id": "67112",
    "name": "03aa89f6e18d873978e5"
  },
  {
    "id": "67145",
    "name": "7ee7b1c57cfde431f3c9"
  },
  {
    "id": "67147",
    "name": "4e98f580d434c4fbb922"
  },
  {
    "id": "67182",
    "name": "84be6db5d87a600c025f"
  },
  {
    "id": "67267",
    "name": "e7bcfa31407b80c12d5e"
  },
  {
    "id": "67367",
    "name": "3f927beb7ffb900d1721"
  },
  {
    "id": "67455",
    "name": "b37bbe3f41579f2b4d58"
  },
  {
    "id": "67551",
    "name": "08bd4171ce44605655cb"
  },
  {
    "id": "67783",
    "name": "7b9593d80474c59921bc"
  },
  {
    "id": "67874",
    "name": "65fbf13f408a750a9569"
  },
  {
    "id": "67953",
    "name": "0f4601ff246bac46afa9"
  },
  {
    "id": "68360",
    "name": "9a2025cfdf5c352deb29"
  },
  {
    "id": "68675",
    "name": "c83c867f087cc6fac978"
  },
  {
    "id": "68906",
    "name": "9245c6f5cc833deaf4c5"
  },
  {
    "id": "68912",
    "name": "9a35be0af5cd74412cb1"
  },
  {
    "id": "68929",
    "name": "57d941045a91c4c991d9"
  },
  {
    "id": "68953",
    "name": "7a2f30c79baa12b48ad0"
  },
  {
    "id": "68994",
    "name": "a0d72b9904d3e5e68bcf"
  },
  {
    "id": "69489",
    "name": "5242dc3890da883be8ac"
  },
  {
    "id": "69712",
    "name": "c2f0b68352a3f97da922"
  },
  {
    "id": "69755",
    "name": "760397c43c597cd90cfb"
  },
  {
    "id": "69836",
    "name": "e5ab7cce2ceff4833ee8"
  },
  {
    "id": "69876",
    "name": "0f7ca8888f0705ad886c"
  },
  {
    "id": "70029",
    "name": "3f339d9840671119a647"
  },
  {
    "id": "70245",
    "name": "4dcf98c35a2b941cfd6d"
  },
  {
    "id": "70301",
    "name": "796c10efb3df79933fd3"
  },
  {
    "id": "70462",
    "name": "9e1b6e58a54068cea0ef"
  },
  {
    "id": "70535",
    "name": "930671e433239e88d33e"
  },
  {
    "id": "70623",
    "name": "29c208fd631d3027e856"
  },
  {
    "id": "70801",
    "name": "85c2fff4a8b9f60739ef"
  },
  {
    "id": "70875",
    "name": "e35fd9cbbac1c2a4b997"
  },
  {
    "id": "71363",
    "name": "c21b7baf1085c6a97083"
  },
  {
    "id": "71379",
    "name": "62dbc71bca478e471fbb"
  },
  {
    "id": "71402",
    "name": "bdb6508ef9cbe8295c32"
  },
  {
    "id": "71478",
    "name": "27b557f8b289f5b01104"
  },
  {
    "id": "71485",
    "name": "8569e1803035c8d71f45"
  },
  {
    "id": "71569",
    "name": "6a60abf5595c07feb312"
  },
  {
    "id": "71575",
    "name": "4d07afbcd2903c984712"
  },
  {
    "id": "71630",
    "name": "90b02206747b1cb78124"
  },
  {
    "id": "71655",
    "name": "8dc52276b52dfc602745"
  },
  {
    "id": "71690",
    "name": "c8eebedc01d6aa5d755a"
  },
  {
    "id": "71692",
    "name": "fccd1c2803ed55df3c50"
  },
  {
    "id": "71718",
    "name": "fe935fe2df1f7a21105f"
  },
  {
    "id": "72033",
    "name": "b7bc9497224843525010"
  },
  {
    "id": "72353",
    "name": "f678d767b438539ce3a6"
  },
  {
    "id": "72501",
    "name": "6cd259c0ffa4b8054a91"
  },
  {
    "id": "72510",
    "name": "8ceb8bd690ce05b127cc"
  },
  {
    "id": "72519",
    "name": "a831c9e86c998bdc27ba"
  },
  {
    "id": "72552",
    "name": "ec68514ce236f792a252"
  },
  {
    "id": "72591",
    "name": "c3072d75b36bb280aedf"
  },
  {
    "id": "72629",
    "name": "ae7d9bf47e34d7020fb7"
  },
  {
    "id": "72722",
    "name": "96ef9459d7da2601159b"
  },
  {
    "id": "72935",
    "name": "be1a5855e095137ec67b"
  },
  {
    "id": "72982",
    "name": "8450f6018424a0d61788"
  },
  {
    "id": "73177",
    "name": "1ff4aa4252fd4df0cd71"
  },
  {
    "id": "73356",
    "name": "d990a509e2e5bdc737e2"
  },
  {
    "id": "73523",
    "name": "51c133ff02f1287628af"
  },
  {
    "id": "73591",
    "name": "6af0f9af5ad8ce6b38d8"
  },
  {
    "id": "73597",
    "name": "bd5eb9c12b2b74f00c42"
  },
  {
    "id": "73634",
    "name": "8bb4ef8abbdc646bce95"
  },
  {
    "id": "73679",
    "name": "b85c3317186c4d2e13d6"
  },
  {
    "id": "73727",
    "name": "ab4649cbb76b72fd2a8c"
  },
  {
    "id": "74067",
    "name": "cc1b82cd5bebfe007f29"
  },
  {
    "id": "74310",
    "name": "50101569183b84902400"
  },
  {
    "id": "74328",
    "name": "ee6b69c7a25a291eb8b1"
  },
  {
    "id": "74488",
    "name": "62948cb418c54759407c"
  },
  {
    "id": "74544",
    "name": "e271f608a82f06d1581c"
  },
  {
    "id": "74562",
    "name": "7ca74a4f6d7bd243f60f"
  },
  {
    "id": "74709",
    "name": "1588abf38747b6ac5db8"
  },
  {
    "id": "74780",
    "name": "a1d5cd58701d3153b5b4"
  },
  {
    "id": "74871",
    "name": "3535109782a4b48de0af"
  },
  {
    "id": "74886",
    "name": "49ffd3140b2afe71b327"
  },
  {
    "id": "74968",
    "name": "2a1ab02dcaf160e7a174"
  },
  {
    "id": "74996",
    "name": "e675ddaf168b0a17bb08"
  },
  {
    "id": "75026",
    "name": "31988e276767015619e9"
  },
  {
    "id": "75309",
    "name": "8f569b23bccee162f709"
  },
  {
    "id": "75336",
    "name": "d1b6d4e62de269fc1802"
  },
  {
    "id": "75442",
    "name": "a6210c8532d271b979e3"
  },
  {
    "id": "75600",
    "name": "221bbd147a021c115006"
  },
  {
    "id": "75619",
    "name": "e1ff2776db2fc0f4f22d"
  },
  {
    "id": "75625",
    "name": "df9bf94ad01ee0051663"
  },
  {
    "id": "75651",
    "name": "7402b76f9f4d1b6ff961"
  },
  {
    "id": "75700",
    "name": "202e4802f923b810966e"
  },
  {
    "id": "75864",
    "name": "f533b2b8883ec0365eba"
  },
  {
    "id": "76141",
    "name": "4306de57311d63efbc05"
  },
  {
    "id": "76156",
    "name": "e91105bf97cc7d817e1b"
  },
  {
    "id": "76188",
    "name": "f71929fbda7cb5d1a2b0"
  },
  {
    "id": "76192",
    "name": "deee41b2f23e08c636f1"
  },
  {
    "id": "76257",
    "name": "002f51b77a34313933f0"
  },
  {
    "id": "77179",
    "name": "6d733656779df3c4b4f8"
  },
  {
    "id": "77230",
    "name": "d49f0e94f85310012b2f"
  },
  {
    "id": "77357",
    "name": "6f1c8ef6d4fd8f8d87d0"
  },
  {
    "id": "77579",
    "name": "8421a78b9456ed750c99"
  },
  {
    "id": "77647",
    "name": "418d97a66fb0480a447a"
  },
  {
    "id": "77703",
    "name": "a50958326c23f21f2c3e"
  },
  {
    "id": "77754",
    "name": "a2b8e1d0859722ebfc7e"
  },
  {
    "id": "77876",
    "name": "48d2be13c28b6dbdb92a"
  },
  {
    "id": "78158",
    "name": "cfc4b82f2ea708b54b1d"
  },
  {
    "id": "78185",
    "name": "9ee9091e5e0a1a3fa076"
  },
  {
    "id": "78230",
    "name": "4e3e1ea7c94c65cedc5e"
  },
  {
    "id": "78294",
    "name": "7e3abeaca80dee1e6dcd"
  },
  {
    "id": "78528",
    "name": "8ccaa554a5aae91a509f"
  },
  {
    "id": "78732",
    "name": "05f56fd99c8cf68a6ee2"
  },
  {
    "id": "78759",
    "name": "d0bb720c3dfbe9625a83"
  },
  {
    "id": "79249",
    "name": "cc83f0d78dd7e1ec0019"
  },
  {
    "id": "79540",
    "name": "49c15f4a870df5375ef7"
  },
  {
    "id": "79913",
    "name": "948c2bc389befc237a24"
  },
  {
    "id": "79995",
    "name": "0a1182e7330fcfef27d4"
  },
  {
    "id": "80068",
    "name": "b24238d7a800720e8913"
  },
  {
    "id": "80099",
    "name": "1d37debd28f22b2b8f56"
  },
  {
    "id": "80197",
    "name": "551e2795c8fcc1e28bd1"
  },
  {
    "id": "80238",
    "name": "f717010cf1a251bb6e9e"
  },
  {
    "id": "80284",
    "name": "926a45529559d2fb2a6b"
  },
  {
    "id": "80372",
    "name": "c601228775dd6a43efd1"
  },
  {
    "id": "80547",
    "name": "875cbb36752c7eaca6c7"
  },
  {
    "id": "80695",
    "name": "63f5b4b8e01036917b9a"
  },
  {
    "id": "80853",
    "name": "dd5c5ab1657e5e645509"
  },
  {
    "id": "81148",
    "name": "fe8a689827b977caf81b"
  },
  {
    "id": "81580",
    "name": "b585ef4f9f9fbd73f121"
  },
  {
    "id": "81603",
    "name": "bd92855a94241997c037"
  },
  {
    "id": "81640",
    "name": "c4bc5d754167845e39f8"
  },
  {
    "id": "81977",
    "name": "1bd161934331dab824ae"
  },
  {
    "id": "82312",
    "name": "29343317ffa3e13faf5b"
  },
  {
    "id": "82761",
    "name": "fc906b2ab9aaf8cc7c93"
  },
  {
    "id": "82786",
    "name": "d95701473c3af3442593"
  },
  {
    "id": "82855",
    "name": "2eff87fef44717b96803"
  },
  {
    "id": "82932",
    "name": "c209a41c8690c3f7e766"
  },
  {
    "id": "82938",
    "name": "b746caa20f93b60efb84"
  },
  {
    "id": "82958",
    "name": "afd0f3b4651b210a31c3"
  },
  {
    "id": "83015",
    "name": "2517423ebaa4854f6530"
  },
  {
    "id": "83064",
    "name": "8c09167a46aec52a295d"
  },
  {
    "id": "83081",
    "name": "cdc2dc81cd12063f5118"
  },
  {
    "id": "83103",
    "name": "2ff216d2c01854312d67"
  },
  {
    "id": "83316",
    "name": "ab0ef632a2be0ddf783d"
  },
  {
    "id": "83376",
    "name": "2419508858829a28b387"
  },
  {
    "id": "83409",
    "name": "fd3941d8c9570a1591ec"
  },
  {
    "id": "83966",
    "name": "66423eb4bbae38f702c5"
  },
  {
    "id": "84166",
    "name": "8ddcee3f039772b208e8"
  },
  {
    "id": "84237",
    "name": "8294491732a2543c39b8"
  },
  {
    "id": "84264",
    "name": "55540f761df1033151ab"
  },
  {
    "id": "84346",
    "name": "cc8136a017266372db94"
  },
  {
    "id": "84380",
    "name": "4dfee48f622152a2a57f"
  },
  {
    "id": "84436",
    "name": "89918f6c95768d4b7930"
  },
  {
    "id": "84441",
    "name": "35f5536ab70ed9287e73"
  },
  {
    "id": "84501",
    "name": "4a93e89bb1aa71079bfc"
  },
  {
    "id": "84562",
    "name": "a1fb70907d29e5c74c56"
  },
  {
    "id": "84584",
    "name": "cc33e828660f965c6b17"
  },
  {
    "id": "84604",
    "name": "82d0ea711b95709ffdd0"
  },
  {
    "id": "84663",
    "name": "3ca88e49798fc9b0d561"
  },
  {
    "id": "84670",
    "name": "adcd717cb2aa3b85f35e"
  },
  {
    "id": "84680",
    "name": "d65d90762b1fd4de736f"
  },
  {
    "id": "84715",
    "name": "f0d6afe64d0a935db664"
  },
  {
    "id": "84781",
    "name": "481e5e48717f9fa05edd"
  },
  {
    "id": "84832",
    "name": "dbdd852a82b15d05d7f9"
  },
  {
    "id": "84894",
    "name": "1960262bf10ace2d4983"
  },
  {
    "id": "84905",
    "name": "e4dae573b92872ac3e3a"
  },
  {
    "id": "84959",
    "name": "a51ebe26fec6e8c27ece"
  },
  {
    "id": "84991",
    "name": "734b44022a26e1fb608c"
  },
  {
    "id": "85004",
    "name": "17bf10e468b2eac6a362"
  },
  {
    "id": "85157",
    "name": "c4052d5851654f1d202e"
  },
  {
    "id": "85293",
    "name": "abfdbfa607ddccdca34f"
  },
  {
    "id": "85318",
    "name": "42c6e8bb88a627e134f2"
  },
  {
    "id": "85572",
    "name": "b0cf75f27577bec2c141"
  },
  {
    "id": "85789",
    "name": "cb5cf256b549aa399048"
  },
  {
    "id": "85903",
    "name": "7b6672f100e987f95943"
  },
  {
    "id": "86045",
    "name": "81ac470f10a97f26c0a8"
  },
  {
    "id": "86335",
    "name": "90e9b1c5565490f3ab94"
  },
  {
    "id": "86438",
    "name": "092096800bb68202a140"
  },
  {
    "id": "86473",
    "name": "fd800a857b1a9222f3a2"
  },
  {
    "id": "86502",
    "name": "5ca48d87f65fc6a5899f"
  },
  {
    "id": "86611",
    "name": "67c16eb57af39694f8f7"
  },
  {
    "id": "86651",
    "name": "8ea702de9c6a99f7afbc"
  },
  {
    "id": "87025",
    "name": "b89325bc0e60315987a0"
  },
  {
    "id": "87283",
    "name": "bb94802f7d7e0059e63f"
  },
  {
    "id": "87319",
    "name": "ac9662067722f523f942"
  },
  {
    "id": "87328",
    "name": "0d4658bcee6b8113925f"
  },
  {
    "id": "87430",
    "name": "391501d4aa1a82f5db89"
  },
  {
    "id": "87440",
    "name": "c2e7faa566bb0636aae6"
  },
  {
    "id": "87468",
    "name": "8ff0b7ae5a1d27b6b152"
  },
  {
    "id": "87485",
    "name": "dd19429d8daaa74b600e"
  },
  {
    "id": "87630",
    "name": "0d9b35ad6cff5d3384ee"
  },
  {
    "id": "87812",
    "name": "cb8531ca64973ece1d61"
  },
  {
    "id": "87847",
    "name": "7987c9ffd4f1a0a678b6"
  },
  {
    "id": "87868",
    "name": "164cb003e04dc2ddedd6"
  },
  {
    "id": "87896",
    "name": "7ad5087903cbfcfd6707"
  },
  {
    "id": "87947",
    "name": "d77e8a9f9758867cfc96"
  },
  {
    "id": "88005",
    "name": "c822c6edb436b2fbe79a"
  },
  {
    "id": "88110",
    "name": "fc7442749b0e77c8b21d"
  },
  {
    "id": "88310",
    "name": "73d9771ef460c7756dfd"
  },
  {
    "id": "88352",
    "name": "2d00f71ad789d14bfaec"
  },
  {
    "id": "88609",
    "name": "4f1bda42e4148b68ba80"
  },
  {
    "id": "89005",
    "name": "8c27d4899f1b12d8f38b"
  },
  {
    "id": "89030",
    "name": "a9ee6e5f2b7c98d92323"
  },
  {
    "id": "89157",
    "name": "fe9e1298e83bb29f8f38"
  },
  {
    "id": "89304",
    "name": "da9d1d8849b5bc1c87c4"
  },
  {
    "id": "89594",
    "name": "3660cf1cd16b59024f5a"
  },
  {
    "id": "89609",
    "name": "89a4b5acda23eeec5e98"
  },
  {
    "id": "89853",
    "name": "8a54268629c67be3ea2c"
  },
  {
    "id": "89938",
    "name": "65e480d4a624ae8a02fa"
  },
  {
    "id": "89975",
    "name": "ebc318490c847155d20b"
  },
  {
    "id": "89984",
    "name": "b5c046f257e8ac6b098e"
  },
  {
    "id": "90034",
    "name": "fce6bfe3376a1ad2062e"
  },
  {
    "id": "90150",
    "name": "e740468e28eebc331737"
  },
  {
    "id": "90630",
    "name": "b5ffbe34cf5b58d8ba9e"
  },
  {
    "id": "90997",
    "name": "25f119e532a2d48d6a92"
  },
  {
    "id": "91011",
    "name": "215e702f77b21fa1cfa4"
  },
  {
    "id": "91033",
    "name": "e0a47747e8d36308dd06"
  },
  {
    "id": "91406",
    "name": "cb0c98ab2af8deba627e"
  },
  {
    "id": "91509",
    "name": "e2093771793040f050d5"
  },
  {
    "id": "91642",
    "name": "50774187fd5f5b6d83b9"
  },
  {
    "id": "91683",
    "name": "d9e9199368a30ae58ed0"
  },
  {
    "id": "91762",
    "name": "32628b064d5ddb78ea46"
  },
  {
    "id": "91912",
    "name": "8c22dba5119676155f70"
  },
  {
    "id": "92012",
    "name": "39af43ea3c8a4c1a22b1"
  },
  {
    "id": "92127",
    "name": "0c173f068659048ced46"
  },
  {
    "id": "92145",
    "name": "f872341d04e6db674e91"
  },
  {
    "id": "92189",
    "name": "db5304a1ddca54d2b51e"
  },
  {
    "id": "92224",
    "name": "02796baa25eb015070fe"
  },
  {
    "id": "92291",
    "name": "91b31cb7f8c25c49bde6"
  },
  {
    "id": "92299",
    "name": "1c4fd69e6183a18cfe50"
  },
  {
    "id": "92447",
    "name": "f1956be2ebfad10bcf7e"
  },
  {
    "id": "92465",
    "name": "f99c1866d2ee0e7e17e0"
  },
  {
    "id": "92662",
    "name": "ca3690f1c14858d1247a"
  },
  {
    "id": "92822",
    "name": "e51887f21349f7e718c7"
  },
  {
    "id": "92827",
    "name": "52fffa58d9938bfefebf"
  },
  {
    "id": "93087",
    "name": "9c8b1bf9e13c87304be3"
  },
  {
    "id": "93364",
    "name": "31f1c645184ec50b6df2"
  },
  {
    "id": "93696",
    "name": "70324cc976f4ad30b56f"
  },
  {
    "id": "93862",
    "name": "643b81b84b5156d91e6e"
  },
  {
    "id": "93922",
    "name": "2622dd75717c549eb959"
  },
  {
    "id": "93953",
    "name": "6adce2ed839e386a7d8f"
  },
  {
    "id": "93997",
    "name": "a97485e90a7aafb5c364"
  },
  {
    "id": "94055",
    "name": "25097e3322acbda8fd0b"
  },
  {
    "id": "94095",
    "name": "3178b75c3cb57a87b819"
  },
  {
    "id": "94157",
    "name": "8473c9b438699c0c8c32"
  },
  {
    "id": "94207",
    "name": "2753891aa13d7da620d1"
  },
  {
    "id": "94232",
    "name": "62f74d3596ccffc16454"
  },
  {
    "id": "94239",
    "name": "348979ae895e1cd91631"
  },
  {
    "id": "94302",
    "name": "b2cfcf95ba668c2882b2"
  },
  {
    "id": "94389",
    "name": "dcb4b32f706692a57b5f"
  },
  {
    "id": "94453",
    "name": "8842482be19e2b9a2026"
  },
  {
    "id": "94489",
    "name": "70cf174ba1bf1ae06987"
  },
  {
    "id": "94736",
    "name": "29e211f2a23b7a22659a"
  },
  {
    "id": "94811",
    "name": "f396f92a6485a2cecc2f"
  },
  {
    "id": "94859",
    "name": "57120870d163237ffd74"
  },
  {
    "id": "95081",
    "name": "33f109350e3152d6d3fb"
  },
  {
    "id": "95132",
    "name": "45d61b67e9040bd4adae"
  },
  {
    "id": "95238",
    "name": "f87cc774f8c021955108"
  },
  {
    "id": "95260",
    "name": "009f34fe53c15a5675c4"
  },
  {
    "id": "95599",
    "name": "8c0261eee5cd7a735ea2"
  },
  {
    "id": "95751",
    "name": "10232cd32becbf687372"
  },
  {
    "id": "95839",
    "name": "87bf32e1ec0f2a0d309e"
  },
  {
    "id": "95937",
    "name": "e78fb3f53ef85f6ecc63"
  },
  {
    "id": "95953",
    "name": "5cfccfd5d8bb601ae5b8"
  },
  {
    "id": "96006",
    "name": "8ab878f2db1496c1c8fe"
  },
  {
    "id": "96043",
    "name": "75abfa37f00e18b5cc9b"
  },
  {
    "id": "96259",
    "name": "a38233a6012266bb3ee7"
  },
  {
    "id": "96359",
    "name": "5a30402fbd3cecf02cc0"
  },
  {
    "id": "96404",
    "name": "630f54506e2558642161"
  },
  {
    "id": "96710",
    "name": "b73de8c1f6970c22ed73"
  },
  {
    "id": "96732",
    "name": "77511cd06a6184fc3ecd"
  },
  {
    "id": "96743",
    "name": "158c9622ba24feced0ae"
  },
  {
    "id": "96938",
    "name": "cd51dee9051d2628140d"
  },
  {
    "id": "97174",
    "name": "dedfa25b9c4c59e82317"
  },
  {
    "id": "97250",
    "name": "b1123d8cfad39550c313"
  },
  {
    "id": "97264",
    "name": "d12d1ff2957d8f5da097"
  },
  {
    "id": "97516",
    "name": "93be055b82794edb2fbe"
  },
  {
    "id": "97539",
    "name": "5d57ee08241ed555b46d"
  },
  {
    "id": "97597",
    "name": "baee0a0c3a6af1ab9846"
  },
  {
    "id": "97621",
    "name": "ff147335e3776f1197b8"
  },
  {
    "id": "97848",
    "name": "6c84a2b8bd3d1611df4d"
  },
  {
    "id": "98027",
    "name": "cfeae829a49ae4e4edc1"
  },
  {
    "id": "98030",
    "name": "725bd7cf0e15936cd08c"
  },
  {
    "id": "98153",
    "name": "7d77ad990124b1d33ad4"
  },
  {
    "id": "98211",
    "name": "ab675634dc16fccdd4f5"
  },
  {
    "id": "98655",
    "name": "1945abad499772b12a08"
  },
  {
    "id": "98847",
    "name": "3f55977b4f8fb2847650"
  },
  {
    "id": "99134",
    "name": "e11a1286b92d8b0d76ff"
  },
  {
    "id": "99146",
    "name": "d82bca575b6f866216f5"
  },
  {
    "id": "99316",
    "name": "7a6538d93b43c603941a"
  },
  {
    "id": "99368",
    "name": "6827e857ef20891eed49"
  },
  {
    "id": "99549",
    "name": "3a233db203f36a66bfa9"
  },
  {
    "id": "99676",
    "name": "b0e7012b6a4c4cb6ae2e"
  }
]